seaplanekit/__init__.py
seaplanekit/api/__init__.py
seaplanekit/api/api_http.py
seaplanekit/api/api_request.py
seaplanekit/api/container_api.py
seaplanekit/api/formation_api.py
seaplanekit/api/formation_configuration_api.py
seaplanekit/api/lock_api.py
seaplanekit/api/metadata_api.py
seaplanekit/api/restrict_api.py
seaplanekit/api/token_api.py
seaplanekit/configuration.py
seaplanekit/logging/__init__.py
seaplanekit/model/__init__.py
seaplanekit/model/compute/__init__.py
seaplanekit/model/compute/active_configuration.py
seaplanekit/model/compute/architecture.py
seaplanekit/model/compute/container.py
seaplanekit/model/compute/flight.py
seaplanekit/model/compute/formation_configuration.py
seaplanekit/model/compute/formation_metadata.py
seaplanekit/model/compute/status.py
seaplanekit/model/errors.py
seaplanekit/model/locks/__init__.py
seaplanekit/model/metadata/__init__.py
seaplanekit/model/provider.py
seaplanekit/model/region.py
seaplanekit/model/restrict/__init__.py
seaplanekit/util/__init__.py
seaplanekit/util/base64url.py
seaplanekit-0.2.0.dist-info/WHEEL
seaplanekit-0.2.0.dist-info/METADATA
seaplanekit-0.2.0.dist-info/RECORD
