Metadata-Version: 2.1
Name: seaplanekit
Version: 0.2.0
Summary: Seaplane Python SDK
Home-page: https://github.com/seaplane-io/seaplane/tree/main/seaplane-sdk/python
License: Apache License
Author: Seaplane IO, Inc.
Requires-Python: >=3.8,<3.11
Classifier: License :: Other/Proprietary License
Classifier: Programming Language :: Python :: 3
Classifier: Programming Language :: Python :: 3.10
Classifier: Programming Language :: Python :: 3.8
Classifier: Programming Language :: Python :: 3.9
Requires-Dist: attrs (==21.4.0)
Requires-Dist: certifi (==2022.6.15)
Requires-Dist: charset-normalizer (==2.1.0)
Requires-Dist: idna (==3.3)
Requires-Dist: iniconfig (==1.1.1)
Requires-Dist: packaging (==21.3)
Requires-Dist: pluggy (==1.0.0)
Requires-Dist: py (==1.11.0)
Requires-Dist: pyparsing (==3.0.9)
Requires-Dist: requests (==2.28.1)
Requires-Dist: requests-mock (>=1.9.3,<2.0.0)
Requires-Dist: returns (>=0.19.0,<0.20.0)
Requires-Dist: simplejson (>=3.17.6,<4.0.0)
Requires-Dist: tomli (==2.0.1)
Requires-Dist: types-requests (>=2.28.0,<3.0.0)
Requires-Dist: types-simplejson (>=3.17.7,<4.0.0)
Requires-Dist: urllib3 (==1.26.9)
Project-URL: Documentation, https://github.com/seaplane-io/seaplane/tree/main/seaplane-sdk/python
Project-URL: Repository, https://github.com/seaplane-io/seaplane/tree/main/seaplane-sdk/python
